odoo/addons/website_sale_order_type/README.rst
odoo/addons/website_sale_order_type/__init__.py
odoo/addons/website_sale_order_type/__manifest__.py
odoo/addons/website_sale_order_type/demo/assets.xml
odoo/addons/website_sale_order_type/i18n/ca.po
odoo/addons/website_sale_order_type/i18n/es.po
odoo/addons/website_sale_order_type/i18n/website_sale_order_type.pot
odoo/addons/website_sale_order_type/models/__init__.py
odoo/addons/website_sale_order_type/models/sale_order.py
odoo/addons/website_sale_order_type/readme/CONTRIBUTORS.rst
odoo/addons/website_sale_order_type/readme/DESCRIPTION.rst
odoo/addons/website_sale_order_type/readme/USAGE.rst
odoo/addons/website_sale_order_type/static/description/icon.png
odoo/addons/website_sale_order_type/static/description/index.html
odoo/addons/website_sale_order_type/static/src/js/website_sale_order_type_tour.js
odoo/addons/website_sale_order_type/tests/__init__.py
odoo/addons/website_sale_order_type/tests/test_website_sale_order_type.py
odoo13_addon_website_sale_order_type-13.0.1.0.1.dev6.dist-info/METADATA
odoo13_addon_website_sale_order_type-13.0.1.0.1.dev6.dist-info/WHEEL
odoo13_addon_website_sale_order_type-13.0.1.0.1.dev6.dist-info/top_level.txt
odoo13_addon_website_sale_order_type-13.0.1.0.1.dev6.dist-info/RECORD
