Metadata-Version: 2.1
Name: odoo13-addon-website-sale-order-type
Version: 13.0.1.0.1.dev6
Summary: This module allows sale_order_type to work with website_sale.
Home-page: https://github.com/OCA/e-commerce
Author: Agile Business Group, Odoo Community Association (OCA)
Author-email: support@odoo-community.org
License: AGPL-3
Platform: UNKNOWN
Classifier: Programming Language :: Python
Classifier: Framework :: Odoo
Classifier: Framework :: Odoo :: 13.0
Classifier: License :: OSI Approved :: GNU Affero General Public License v3
Classifier: Development Status :: 4 - Beta
Requires-Python: >=3.5
Requires-Dist: odoo13-addon-sale-order-type
Requires-Dist: odoo <13.1dev,>=13.0a
